tlnp_lib/__init__.py
tlnp_lib/lambda_tuner.py
tlnp_lib/loss.py
tlnp_lib/naive_neyman_pearson.py
tlnp_lib/optimizers.py
tlnp_lib/point_selection_utils.py
tlnp_lib/runner.py
tlnp_lib/training_logger.py
tlnp_lib/training_utils.py
tlnp_lib/transfer_learning_neyman_pearson.py
tlnp_lib-0.1.1.dist-info/LICENSE
tlnp_lib-0.1.1.dist-info/METADATA
tlnp_lib-0.1.1.dist-info/WHEEL
tlnp_lib-0.1.1.dist-info/top_level.txt
tlnp_lib-0.1.1.dist-info/RECORD
