Metadata-Version: 2.2
Name: tlnp-lib
Version: 0.1.1
Summary: A framework for transfer learning with a Neyman Pearson approach
Author-email: "Eitan J. Neugut" <eitan.neugut@columbia.edu>, Mohammadreza Mousavi Kalan <mohammad.mousavikalan@gmail.com>
License: BSD 3-Clause License
Project-URL: Homepage, https://github.com/eneugut/transfer-learning-neyman-pearson
Project-URL: Repository, https://github.com/eneugut/transfer-learning-neyman-pearson
Project-URL: Issues, https://github.com/eneugut/transfer-learning-neyman-pearson/issues
Requires-Python: >=3.8
License-File: LICENSE
Requires-Dist: numpy==1.26.4
Requires-Dist: torch
Requires-Dist: matplotlib
Requires-Dist: pandas
Requires-Dist: scikit-learn
Requires-Dist: tabulate
Requires-Dist: seaborn
